Modified dual-CLCG/modified CLCG/LCG/register.v
module register
#(parameter N = 4)
(
	input wire clk,
	input wire [N-1:0] p_in,
	input wire shift,
	input wire rst,
	input wire [N-1:0] r,
	output wire [N-1:0] p_out
);
//signals
reg [N-1:0] r_contents;
wire [N-1:0] r_next;
//register
always @(posedge clk or posedge rst)
begin
	if(rst)
		r_contents <= 0;
	else 
		begin
			r_contents <= r_next;	
		end
end
//next state logic
assign r_next = (shift==1) ? p_in<<r :
				p_in;
//output logic
assign p_out = r_contents;

endmodule

Modified dual-CLCG/modified CLCG/LCG/adder.v
module adder
#(parameter N = 4)
(
	input wire [N-1:0] b,
	input wire [N-1:0] x_i,
	input wire [N-1:0] x_a,
	input wire [N-1:0] m,
	output wire [N-1:0] sum
);
assign sum = (b + x_i + x_a)&(m-1);
endmodule

Modified dual-CLCG/modified CLCG/LCG/mux.v
module muxer
#(parameter N = 4)
(
	input wire [N-1:0] A,
	input wire [N-1:0] B,
	input wire sel,
	output wire [N-1:0] out
);
assign out = (sel==1) ? A : B;
endmodule

Modified dual-CLCG/modified CLCG/LCG/LCG.v
`include "mux.v"
`include "register.v"
`include "adder.v"



module LCG
(
	input wire start,
	input wire [3:0] seed,
	input wire [3:0] a,
	input wire [3:0] b,
	input wire [3:0] r,
	input wire [3:0] m,
	input wire rst,
	output wire [3:0] x_ip1,
	input wire clk1,
	input wire clk2
);
//signals
wire [3:0] x_i;
wire [3:0] x_a;
wire [3:0] adder_out;
supply0 gnd;
supply1 vcc;
//instantiation of datapath
muxer M0 		(x_ip1,seed, start, x_i);
adder A0 	(b, x_i, x_a, m, adder_out);
register R0 (clk2, adder_out, gnd, rst, r, x_ip1);
register S0 (clk1, x_i, vcc, rst, r, x_a);

endmodule

Modified dual-CLCG/modified CLCG/LCG/LCG_test.v
module LCG_test;
//signals
reg start;
reg [3:0] seed;
reg [3:0] a;
reg [3:0] b;
reg [3:0] r;
reg [3:0] m;
reg rst;
wire [3:0] x_i1;
reg clk1;
reg clk2;
//instantiation
LCG uut (start, seed, a, b, r, m, rst, x_i1, clk1,clk2);
//clock
always
	#5 clk1 = ~clk1;
always 
        #10 clk2 = ~clk2;

//dumping
initial
	begin
	$dumpfile("lcgg.vcd");
        $dumpvars(0,LCG_test);
        clk1 = 1'b0;
        clk2 = 1'b0;
        start = 1'b0;
        rst = 1'b0;
        seed = 3;
        a = 5;
        b = 1;
        r = 2;
        m = 8;
        #1 rst = 1'b1;
        #2 rst = 1'b0;
        #20 start = 1'b1;

        #300 $finish;
	end
endmodule

Modified dual-CLCG/modified CLCG/LCG/lcgg.vcd
$date
	Thu Mar 11 19:14:43 2021
$end
$version
	Icarus Verilog
$end
$timescale
	1s
$end
$scope module LCG_test $end
$var wire 4 ! x_i1 [3:0] $end
$var reg 4 " a [3:0] $end
$var reg 4 # b [3:0] $end
$var reg 1 $ clk1 $end
$var reg 1 % clk2 $end
$var reg 4 & m [3:0] $end
$var reg 4 ' r [3:0] $end
$var reg 1 ( rst $end
$var reg 4 ) seed [3:0] $end
$var reg 1 * start $end
$scope module uut $end
$var wire 4 + a [3:0] $end
$var wire 4 , b [3:0] $end
$var wire 1 $ clk1 $end
$var wire 1 % clk2 $end
$var wire 1 - gnd $end
$var wire 4 . m [3:0] $end
$var wire 4 / r [3:0] $end
$var wire 1 ( rst $end
$var wire 4 0 seed [3:0] $end
$var wire 1 * start $end
$var wire 1 1 vcc $end
$var wire 4 2 x_ip1 [3:0] $end
$var wire 4 3 x_i [3:0] $end
$var wire 4 4 x_a [3:0] $end
$var wire 4 5 adder_out [3:0] $end
$scope module A0 $end
$var wire 4 6 b [3:0] $end
$var wire 4 7 m [3:0] $end
$var wire 4 8 sum [3:0] $end
$var wire 4 9 x_i [3:0] $end
$var wire 4 : x_a [3:0] $end
$upscope $end
$scope module M0 $end
$var wire 4 ; B [3:0] $end
$var wire 1 * sel $end
$var wire 4 < out [3:0] $end
$var wire 4 = A [3:0] $end
$upscope $end
$scope module R0 $end
$var wire 1 % clk $end
$var wire 4 > p_in [3:0] $end
$var wire 4 ? r [3:0] $end
$var wire 1 ( rst $end
$var wire 1 - shift $end
$var wire 4 @ r_next [3:0] $end
$var wire 4 A p_out [3:0] $end
$var reg 4 B r_contents [3:0] $end
$upscope $end
$scope module S0 $end
$var wire 1 $ clk $end
$var wire 4 C p_in [3:0] $end
$var wire 4 D r [3:0] $end
$var wire 1 ( rst $end
$var wire 1 1 shift $end
$var wire 4 E r_next [3:0] $end
$var wire 4 F p_out [3:0] $end
$var reg 4 G r_contents [3:0] $end
$upscope $end
$upscope $end
$upscope $end
$enddefinitions $end
#0
$dumpvars
bx G
bx F
b1100 E
b10 D
b11 C
bx B
bx A
b0xxx @
b10 ?
b0xxx >
bx =
b11 <
b11 ;
bx :
b11 9
b0xxx 8
b1000 7
b1 6
b0xxx 5
bx 4
b11 3
bx 2
11
b11 0
b10 /
b1000 .
0-
b1 ,
b101 +
0*
b11 )
0(
b10 '
b1000 &
0%
0$
b1 #
b101 "
bx !
$end
#1
b100 @
b100 5
b100 8
b100 >
b0 !
b0 2
b0 =
b0 A
b0 B
b0 4
b0 :
b0 F
b0 G
1(
#3
0(
#5
b0 @
b0 5
b0 8
b0 >
b1100 4
b1100 :
b1100 F
b1100 G
1$
#10
0$
1%
#15
1$
#20
0$
0%
#23
b101 @
b0 E
b101 5
b101 8
b101 >
b0 3
b0 9
b0 <
b0 C
1*
#25
b1 @
b1 5
b1 8
b1 >
b0 4
b0 :
b0 F
b0 G
1$
#30
b10 @
b100 E
b10 5
b10 8
b10 >
b1 3
b1 9
b1 <
b1 C
b1 !
b1 2
b1 =
b1 A
b1 B
0$
1%
#35
b110 @
b110 5
b110 8
b110 >
b100 4
b100 :
b100 F
b100 G
1$
#40
0$
0%
#45
1$
#50
b11 @
b1000 E
b11 5
b11 8
b11 >
b110 3
b110 9
b110 <
b110 C
b110 !
b110 2
b110 =
b110 A
b110 B
0$
1%
#55
b111 @
b111 5
b111 8
b111 >
b1000 4
b1000 :
b1000 F
b1000 G
1$
#60
0$
0%
#65
1$
#70
b0 @
b1100 E
b0 5
b0 8
b0 >
b111 3
b111 9
b111 <
b111 C
b111 !
b111 2
b111 =
b111 A
b111 B
0$
1%
#75
b100 @
b100 5
b100 8
b100 >
b1100 4
b1100 :
b1100 F
b1100 G
1$
#80
0$
0%
#85
1$
#90
b1 @
b0 E
b1 5
b1 8
b1 >
b100 3
b100 9
b100 <
b100 C
b100 !
b100 2
b100 =
b100 A
b100 B
0$
1%
#95
b101 @
b101 5
b101 8
b101 >
b0 4
b0 :
b0 F
b0 G
1$
#100
0$
0%
#105
1$
#110
b110 @
b100 E
b110 5
b110 8
b110 >
b101 3
b101 9
b101 <
b101 C
b101 !
b101 2
b101 =
b101 A
b101 B
0$
1%
#115
b10 @
b10 5
b10 8
b10 >
b100 4
b100 :
b100 F
b100 G
1$
#120
0$
0%
#125
1$
#130
b111 @
b1000 E
b111 5
b111 8
b111 >
b10 3
b10 9
b10 <
b10 C
b10 !
b10 2
b10 =
b10 A
b10 B
0$
1%
#135
b11 @
b11 5
b11 8
b11 >
b1000 4
b1000 :
b1000 F
b1000 G
1$
#140
0$
0%
#145
1$
#150
b100 @
b1100 E
b100 5
b100 8
b100 >
b11 3
b11 9
b11 <
b11 C
b11 !
b11 2
b11 =
b11 A
b11 B
0$
1%
#155
b0 @
b0 5
b0 8
b0 >
b1100 4
b1100 :
b1100 F
b1100 G
1$
#160
0$
0%
#165
1$
#170
b101 @
b0 E
b101 5
b101 8
b101 >
b0 3
b0 9
b0 <
b0 C
b0 !
b0 2
b0 =
b0 A
b0 B
0$
1%
#175
b1 @
b1 5
b1 8
b1 >
b0 4
b0 :
b0 F
b0 G
1$
#180
0$
0%
#185
1$
#190
b10 @
b100 E
b10 5
b10 8
b10 >
b1 3
b1 9
b1 <
b1 C
b1 !
b1 2
b1 =
b1 A
b1 B
0$
1%
#195
b110 @
b110 5
b110 8
b110 >
b100 4
b100 :
b100 F
b100 G
1$
#200
0$
0%
#205
1$
#210
b11 @
b1000 E
b11 5
b11 8
b11 >
b110 3
b110 9
b110 <
b110 C
b110 !
b110 2
b110 =
b110 A
b110 B
0$
1%
#215
b111 @
b111 5
b111 8
b111 >
b1000 4
b1000 :
b1000 F
b1000 G
1$
#220
0$
0%
#225
1$
#230
b0 @
b1100 E
b0 5
b0 8
b0 >
b111 3
b111 9
b111 <
b111 C
b111 !
b111 2
b111 =
b111 A
b111 B
0$
1%
#235
b100 @
b100 5
b100 8
b100 >
b1100 4
b1100 :
b1100 F
b1100 G
1$
#240
0$
0%
#245
1$
#250
b1 @
b0 E
b1 5
b1 8
b1 >
b100 3
b100 9
b100 <
b100 C
b100 !
b100 2
b100 =
b100 A
b100 B
0$
1%
#255
b101 @
b101 5
b101 8
b101 >
b0 4
b0 :
b0 F
b0 G
1$
#260
0$
0%
#265
1$
#270
b110 @
b100 E
b110 5
b110 8
b110 >
b101 3
b101 9
b101 <
b101 C
b101 !
b101 2
b101 =
b101 A
b101 B
0$
1%
#275
b10 @
b10 5
b10 8
b10 >
b100 4
b100 :
b100 F
b100 G
1$
#280
0$
0%
#285
1$
#290
b111 @
b1000 E
b111 5
b111 8
b111 >
b10 3
b10 9
b10 <
b10 C
b10 !
b10 2
b10 =
b10 A
b10 B
0$
1%
#295
b11 @
b11 5
b11 8
b11 >
b1000 4
b1000 :
b1000 F
b1000 G
1$
#300
0$
0%
#305
1$
#310
b100 @
b1100 E
b100 5
b100 8
b100 >
b11 3
b11 9
b11 <
b11 C
b11 !
b11 2
b11 =
b11 A
b11 B
0$
1%
#315
b0 @
b0 5
b0 8
b0 >
b1100 4
b1100 :
b1100 F
b1100 G
1$
