Blum-Blum-Shub Generator/DP/mr2mmm_CON.v

module mr2mmm_CON
#(parameter M = 8)
(
  input wire start,
  input wire clk, rst,
  output reg [1:0] R1_en,
  output reg [1:0] done,
  output reg [1:0] SR1_en,
  output reg [1:0] SR2_en,
  output reg clrR1, clrR2, clrSR1, clrSR2,
  output reg step,
  input wire [M-1:0] n
);
//params
localparam INITIAL = 3'b000, START = 3'b001, DONE = 3'b010, S0 = 3'b011, S1 = 3'b100, S2 = 3'b101, CHECK = 3'b110;
localparam DO_NOTHING = 2'b00, SHIFT_LEFT = 2'b01, SHIFT_RIGHT = 2'b10, PARALLEL_LOAD = 2'b11;
//signals
reg [2:0] r_state;
reg [2:0] r_next;
reg [M-1:0] counter;
//register
always @ (posedge clk or posedge rst)
begin
  if(rst)
    r_state <= INITIAL;
  else 
    r_state <= r_next;
end

always @(posedge rst)
    begin
        step = 0;
    end

//OP and NS logic
always @(*)
  begin
    R1_en = 2'b00;
    done = 2'b00;
    SR1_en = 2'b00;
    SR2_en = 2'b00;
    clrR1 = 0;
    clrSR2 = 0;
    clrSR1 = 0;
    clrR2 = 0;
    r_next = r_state;
    case (r_state)
      INITIAL :
      begin
      //#1;
        counter = 0;
        if (start)
          r_next = START;
        else 
          r_next = INITIAL;
      end

      START :
      begin
      //#1;
        clrR2 = 0;
        SR1_en = 2'b11;
        clrSR2 = 1;
        clrR1 = 1;
        r_next = CHECK;
      end

      CHECK :
      begin
      //#1;
        if(counter<n)
            r_next = S0;
        else 
            r_next = DONE;
      end

      S0 :
      begin
      //#1;
        SR2_en = PARALLEL_LOAD;
        r_next = S1;
      end

      S1 :
      begin
      //#1;
        r_next = S2;
        SR2_en = SHIFT_RIGHT;
      end

      S2 :
      begin
      //#1;
        R1_en = PARALLEL_LOAD;
        SR1_en = SHIFT_RIGHT;
        counter = counter + 1;
        r_next = CHECK;
      end

      DONE :
      begin
      //#1;
        if(step==0)
            begin
                r_next = INITIAL;
                step = 1; 
            end
        else
            begin
                step = 0;
                r_next = INITIAL;
                done = PARALLEL_LOAD; 
            end
      end
    endcase
  end
endmodule

Blum-Blum-Shub Generator/DP/MR2MMM/op3adder.v
module op3adder
#(parameter N = 8)
(
	input wire [N-1:0] in1,
	input wire [N-1:0] in2,
	input wire [N-1:0] in3,
	output wire [N-1:0] sum
);

assign sum = in1 + in2 + in3;

endmodule

Blum-Blum-Shub Generator/DP/op2adder.v
module op2adder
#(parameter N = 8)
(
	input wire [N-1:0] in1,
	input wire [N-1:0] in2,
	output wire [N-1:0] sum,
	output wire cy
);

assign {cy,sum} = in1 - in2;

endmodule

Blum-Blum-Shub Generator/DP/mux2_1.v
module mux2_1
#(parameter N = 8)
(
	input wire [N-1:0] A,
	input wire [N-1:0] B,
	input wire sel,
	output wire [N-1:0] out
);
assign out = (sel==1) ? A : B;
endmodule

Blum-Blum-Shub Generator/DP/mux4_1.v


module mux4_1
#(parameter N = 8)
(
	input wire [N-1:0] A,
	input wire [N-1:0] B,
	input wire [N-1:0] C,
	input wire [N-1:0] D,
	input wire [1:0] sel,
	output wire [N-1:0] out
);
wire [N-1:0] w [1:0];
mux2_1 #(.N(N))M0	(w[0], w[1], sel[1], out);
mux2_1 #(.N(N))M1 	(C, D, sel[0], w[1]);
mux2_1 #(.N(N))M2 	(A, B, sel[0], w[0]);
endmodule

Blum-Blum-Shub Generator/DP/register.v
module register
#(parameter N = 8)
(
    input wire clk, reset,
    input wire [1:0] data_ctrl,
    input wire clr,
    input wire [N-1:0] p_in,
    output wire [N-1:0] p_out,
    output wire s_out
);
//params
localparam DO_NOTHING = 2'b00, SHIFT_LEFT = 2'b01, SHIFT_RIGHT = 2'b10, PARALLEL_LOAD = 2'b11;
//signals
reg [N-1:0] r_contents;
wire [N-1:0] r_next;

//register
always @(posedge clk or posedge reset)
    begin
        if(reset || clr) r_contents <= 0;
        else r_contents <= r_next;
    end

//next state logic
assign r_next = (data_ctrl==DO_NOTHING) ? r_contents : 
                (data_ctrl==SHIFT_RIGHT) ? {1'b0, r_contents[N-1:1]} :
                (data_ctrl==SHIFT_LEFT) ? {r_contents[N-2:0], 1'b0} : 
                (data_ctrl==PARALLEL_LOAD) ? p_in :
                r_contents;

//output logic
assign p_out = r_contents;
assign s_out = r_contents[0];

endmodule

Blum-Blum-Shub Generator/DP/mr2mmm_DP.v
`include "mux4_1.v"
`include "op2adder.v"
`include "op3adder.v"
`include "register.v"

module mr2mmm_DP
#(parameter M = 8)
(
	input wire clk, rst,
	input wire [1:0] R1_en,
	input wire [1:0] done,
	input wire [1:0] SR1_en,
	input wire [1:0] SR2_en,
	input wire clrR1, clrR2, clrSR1, clrSR2,
	input wire step,
	input wire [M-1:0] A, B, C, N, n,
	output wire [M+1:0] out
);
//signals
wire [M+1:0] R1_kp1, R1_k, M2_k, M3_k, M1_k, w, SR1_k;
wire [M+1:0] A_3out, A_2out;
wire cy, q0;
supply0 gnd;
//extra reg
reg [M+1:0] S;
always @(posedge step)
	S <= R1_k;
//q0 gen
xor X0 (q0, R1_k[0], M2_k[0]);
assign w = {1024{q0}} & N;
//instantiation
register #(.N(M+2)) R1  (clk, rst, R1_en, clrR1, R1_kp1, R1_k, gnd);
register #(.N(M+2)) R2  (clk, gnd, done,clrR2, M3_k, out, gnd);
register #(.N(M)) SR1 (clk, rst, SR1_en,clrSR1, M1_k, SR1_k, gnd);
register #(.N(M+2)) SR2 (clk, rst, SR2_en,clrSR2, A_3out, R1_kp1, gnd);
mux2_1 #(.N(M)) M1    (C, A, step, M1_k);
mux4_1 #(.N(M+2)) M2 	  (S, 1024'd0, B, 1024'd0, {step,SR1_k[0]}, M2_k);
mux2_1 #(.N(M+2)) M3 	  (R1_kp1, A_2out, cy, M3_k);
op2adder #(.N(M+2)) A_2 (R1_kp1, N, A_2out, cy);
op3adder #(.N(M+2)) A_3 (R1_k, M2_k, w, A_3out);
endmodule

Blum-Blum-Shub Generator/DP/bbs.v
`include "mr2mmm_DP.v"
`include "mr2mmm_CON.v"
`include "mux2_1.v"
module bbs
#(parameter M = 16)
(
	input wire clk, rst, start, load,
	input wire [M-1:0] seed, C, N, n,
	output wire b_i
);
//signals
wire [M-1:0] x_i, x_ip1, Z; 
wire [1:0] R1_en, done, SR1_en, SR2_en;
//op reg
reg [M-1:0] b;
always @(Z)
	b <= Z;
assign b_i = b[0];
assign x_ip1 = b; 
//instantiation
mux2_1 #(.N(M))M0 (x_ip1, seed, load, x_i);
mr2mmm_DP #(.M(M))datapath(clk, rst, R1_en, done, SR1_en, SR2_en, clrR1, clrR2, clrSR1, clrSR2, step, x_i, x_i, C, N, n, Z);
mr2mmm_CON #(.M(M))controller(start, clk, rst, R1_en, done, SR1_en, SR2_en, clrR1, clrR2, clrSR1, clrSR2, step, n);
endmodule

Blum-Blum-Shub Generator/DP/bbs_test.v
`timescale 1ns/10ps
module bbs_test
#(parameter M = 1024);
//signals
reg clk, rst, start, load;
reg [M-1:0] seed, C, N, n;
wire b_i;
//instantiation
bbs #(.M(1024))uut (clk, rst, start, load,seed, C, N, n,b_i);

//dumping
initial
begin
	$dumpfile("mmm.vcd");
    $dumpvars(0,bbs_test);
    clk = 1'b0;
    rst = 1'b0;
    load = 1'b0;
    start = 1'b0;
    seed = 1024'd323809140;
    N = 1024'd1200000003730000000273;
    n = 71;
    C = 1024'd448256546290935196720;
    #2 rst = 1'b1;
    #1 rst = 1'b0;
    repeat(2) @(negedge clk);
    #2 start = 1'b1;
//  #110000 load = 1'b1;
    #100000 $finish;
end

//clock
always
    #5 clk = ~clk;
//load sig
always @(b_i)
    load = 1'b1;
endmodule

Blum-Blum-Shub Generator/DP/testvcd.vcd
$date
	Sun Apr 11 19:19:18 2021
$end
$version
	GTKWave Analyzer v3.3.100 (w)1999-2019 BSI
$end
$timescale
	10ps
$end
$scope module bbs_test $end
$var wire 1 " b_i $end
$upscope $end
$enddefinitions $end
$dumpvars
#0
x"
#73500
1"
#217500
0"
#361500
1"
#433500
0"
#505500
1"
#577500
0"
#937500
1"
